[
  {
    "chain_id": null,
    "execution_time_ms": 22.3851,
    "generation_time_ms": 75.0778,
    "middleware_overhead_ms": 97.46289999999999,
    "middleware_overhead_percent": 131.73955651074925,
    "sui_time_ms": 73.98150000000001,
    "total_size_bytes": 396,
    "total_time_ms": 97.4653,
    "transaction_type": "python",
    "verification_attempts": null,
    "verification_time_ms": null,
    "verified": null
  },
  {
    "chain_id": null,
    "execution_time_ms": 0.1408,
    "generation_time_ms": 30.7502,
    "middleware_overhead_ms": 30.891,
    "middleware_overhead_percent": 101.05963601388422,
    "sui_time_ms": 30.5671,
    "total_size_bytes": 396,
    "total_time_ms": 30.8937,
    "transaction_type": "python",
    "verification_attempts": null,
    "verification_time_ms": null,
    "verified": null
  },
  {
    "chain_id": null,
    "execution_time_ms": 0.12210000000000001,
    "generation_time_ms": 28.945700000000002,
    "middleware_overhead_ms": 29.067800000000002,
    "middleware_overhead_percent": 100.92075021005049,
    "sui_time_ms": 28.8026,
    "total_size_bytes": 396,
    "total_time_ms": 29.0799,
    "transaction_type": "python",
    "verification_attempts": null,
    "verification_time_ms": null,
    "verified": null
  },
  {
    "chain_id": null,
    "execution_time_ms": 0.1401,
    "generation_time_ms": 31.1705,
    "middleware_overhead_ms": 31.3106,
    "middleware_overhead_percent": 100.94006898997388,
    "sui_time_ms": 31.019000000000002,
    "total_size_bytes": 396,
    "total_time_ms": 31.3139,
    "transaction_type": "python",
    "verification_attempts": null,
    "verification_time_ms": null,
    "verified": null
  },
  {
    "chain_id": null,
    "execution_time_ms": 0.1346,
    "generation_time_ms": 31.297600000000003,
    "middleware_overhead_ms": 31.4322,
    "middleware_overhead_percent": 100.92246242562987,
    "sui_time_ms": 31.1449,
    "total_size_bytes": 396,
    "total_time_ms": 31.435699999999997,
    "transaction_type": "python",
    "verification_attempts": null,
    "verification_time_ms": null,
    "verified": null
  }
]