[
  {
    "execution_time_ms": 100.2874,
    "generation_time_ms": 428.89709999999997,
    "sui_time_ms": 237.6953,
    "total_size_bytes": 2696,
    "total_time_ms": 529.2086,
    "transaction_type": "weather"
  },
  {
    "execution_time_ms": 119.3899,
    "generation_time_ms": 10.5381,
    "sui_time_ms": 10.3712,
    "total_size_bytes": 977,
    "total_time_ms": 129.9399,
    "transaction_type": "python"
  },
  {
    "execution_time_ms": 10.0168,
    "generation_time_ms": 10.716800000000001,
    "sui_time_ms": 10.5844,
    "total_size_bytes": 851,
    "total_time_ms": 20.7381,
    "transaction_type": "javascript"
  },
  {
    "execution_time_ms": 3.0628,
    "generation_time_ms": 9.271899999999999,
    "sui_time_ms": 8.9017,
    "total_size_bytes": 3101,
    "total_time_ms": 12.3405,
    "transaction_type": "flight_delay"
  },
  {
    "execution_time_ms": 165.28580000000002,
    "generation_time_ms": 9.8832,
    "sui_time_ms": 9.289800000000001,
    "total_size_bytes": 2780,
    "total_time_ms": 175.1751,
    "transaction_type": "flight_insurance"
  },
  {
    "execution_time_ms": 2.8175000000000003,
    "generation_time_ms": 190.4072,
    "sui_time_ms": 73.85260000000001,
    "total_size_bytes": 2696,
    "total_time_ms": 193.23319999999998,
    "transaction_type": "weather"
  },
  {
    "execution_time_ms": 29.952199999999998,
    "generation_time_ms": 48.3959,
    "sui_time_ms": 48.242,
    "total_size_bytes": 977,
    "total_time_ms": 78.3532,
    "transaction_type": "python"
  },
  {
    "execution_time_ms": 8.1532,
    "generation_time_ms": 10.6159,
    "sui_time_ms": 10.503,
    "total_size_bytes": 851,
    "total_time_ms": 18.773999999999997,
    "transaction_type": "javascript"
  },
  {
    "execution_time_ms": 1.4813999999999998,
    "generation_time_ms": 8.8697,
    "sui_time_ms": 8.6355,
    "total_size_bytes": 3101,
    "total_time_ms": 10.3558,
    "transaction_type": "flight_delay"
  },
  {
    "execution_time_ms": 1.6739000000000002,
    "generation_time_ms": 11.417,
    "sui_time_ms": 10.961200000000002,
    "total_size_bytes": 2780,
    "total_time_ms": 13.0968,
    "transaction_type": "flight_insurance"
  },
  {
    "execution_time_ms": 1.7037,
    "generation_time_ms": 99.8544,
    "sui_time_ms": 16.9054,
    "total_size_bytes": 2696,
    "total_time_ms": 101.5708,
    "transaction_type": "weather"
  },
  {
    "execution_time_ms": 37.496300000000005,
    "generation_time_ms": 18.7911,
    "sui_time_ms": 18.620500000000003,
    "total_size_bytes": 977,
    "total_time_ms": 56.2924,
    "transaction_type": "python"
  },
  {
    "execution_time_ms": 8.9599,
    "generation_time_ms": 27.9349,
    "sui_time_ms": 27.7089,
    "total_size_bytes": 851,
    "total_time_ms": 36.8994,
    "transaction_type": "javascript"
  },
  {
    "execution_time_ms": 1.4951999999999999,
    "generation_time_ms": 20.666400000000003,
    "sui_time_ms": 20.4468,
    "total_size_bytes": 3101,
    "total_time_ms": 22.1663,
    "transaction_type": "flight_delay"
  },
  {
    "execution_time_ms": 1.5147,
    "generation_time_ms": 11.663599999999999,
    "sui_time_ms": 11.243599999999999,
    "total_size_bytes": 2780,
    "total_time_ms": 13.1842,
    "transaction_type": "flight_insurance"
  },
  {
    "execution_time_ms": 1.8691,
    "generation_time_ms": 122.9611,
    "sui_time_ms": 9.1405,
    "total_size_bytes": 2696,
    "total_time_ms": 124.83890000000001,
    "transaction_type": "weather"
  },
  {
    "execution_time_ms": 37.165299999999995,
    "generation_time_ms": 10.430200000000001,
    "sui_time_ms": 10.261299999999999,
    "total_size_bytes": 977,
    "total_time_ms": 47.5997,
    "transaction_type": "python"
  },
  {
    "execution_time_ms": 9.1665,
    "generation_time_ms": 42.126,
    "sui_time_ms": 42.0244,
    "total_size_bytes": 851,
    "total_time_ms": 51.2966,
    "transaction_type": "javascript"
  },
  {
    "execution_time_ms": 3.0176,
    "generation_time_ms": 44.586,
    "sui_time_ms": 44.0312,
    "total_size_bytes": 3101,
    "total_time_ms": 47.6109,
    "transaction_type": "flight_delay"
  },
  {
    "execution_time_ms": 1.8175000000000001,
    "generation_time_ms": 25.699099999999998,
    "sui_time_ms": 24.690199999999997,
    "total_size_bytes": 2780,
    "total_time_ms": 27.523200000000003,
    "transaction_type": "flight_insurance"
  },
  {
    "execution_time_ms": 2.4681,
    "generation_time_ms": 131.6715,
    "sui_time_ms": 19.5016,
    "total_size_bytes": 2696,
    "total_time_ms": 134.1491,
    "transaction_type": "weather"
  },
  {
    "execution_time_ms": 29.476300000000002,
    "generation_time_ms": 25.9156,
    "sui_time_ms": 25.5373,
    "total_size_bytes": 977,
    "total_time_ms": 55.3978,
    "transaction_type": "python"
  },
  {
    "execution_time_ms": 8.423699999999998,
    "generation_time_ms": 11.466099999999999,
    "sui_time_ms": 11.2477,
    "total_size_bytes": 851,
    "total_time_ms": 19.8939,
    "transaction_type": "javascript"
  },
  {
    "execution_time_ms": 1.7310999999999999,
    "generation_time_ms": 9.9484,
    "sui_time_ms": 9.696200000000001,
    "total_size_bytes": 3101,
    "total_time_ms": 11.6853,
    "transaction_type": "flight_delay"
  },
  {
    "execution_time_ms": 1.4724,
    "generation_time_ms": 9.6946,
    "sui_time_ms": 9.2446,
    "total_size_bytes": 2780,
    "total_time_ms": 11.1732,
    "transaction_type": "flight_insurance"
  }
]